bcd.v
module bcd(clk, rst_syn,out); 
input clk;
input rst_syn;
output[3:0] out;
reg [3:0] out;

always@ (posedge clk)
begin
    if(!rst_syn)
        out=0;
    else if(out ==9)
        out=0;
    else    
        out=out+1;
end
endmodule

bcd_tb.v
`timescale 1ns/1ps
module  bcd_tb;
reg clk;
reg rst_n;
wire [3:0] out;

parameter  PERIOD=20 ;
parameter  real DUTY_CUCLE =0.5;
parameter  OFFSET =0;
initial begin
    #OFFSET;
    forever 
        begin
        clk=1'b1;
        #(PERIOD-(PERIOD*DUTY_CUCLE))   clk=1'b0;
        #(PERIOD*DUTY_CUCLE);
        end
end

initial begin
    rst_n = 1'b0;
    #5 rst_n = 1'b1;
    #195 rst_n =1'b0;
    #5 rst_n = 1'b1;
    #55 $finish;
end
initial begin
    $dumpfile("bcd.vcd");
    $dumpvars(0, bcd_1);
end
bcd bcd_1(.clk(clk),
          .rst_syn(rst_n),
          .out(out));
endmodule

bcd.vcd
$date
	Thu May 05 22:52:18 2022
$end
$version
	Icarus Verilog
$end
$timescale
	1ps
$end
$scope module bcd_tb $end
$scope module bcd_1 $end
$var wire 1 ! clk $end
$var wire 1 " rst_syn $end
$var reg 4 # out [3:0] $end
$upscope $end
$upscope $end
$enddefinitions $end
#0
$dumpvars
b0 #
0"
1!
$end
#5000
1"
#10000
0!
#20000
b1 #
1!
#30000
0!
#40000
b10 #
1!
#50000
0!
#60000
b11 #
1!
#70000
0!
#80000
b100 #
1!
#90000
0!
#100000
b101 #
1!
#110000
0!
#120000
b110 #
1!
#130000
0!
#140000
b111 #
1!
#150000
0!
#160000
b1000 #
1!
#170000
0!
#180000
b1001 #
1!
#190000
0!
#200000
b0 #
1!
0"
#205000
1"
#210000
0!
#220000
b1 #
1!
#230000
0!
#240000
b10 #
1!
#250000
0!
#260000
b11 #
1!
